yunhu_usdk/__init__.py
yunhu_usdk/__main__.py
yunhu_usdk/cli.py
yunhu_usdk/usdk.py
yunhu_usdk/api/__init__.py
yunhu_usdk/api/edit.py
yunhu_usdk/api/person.py
yunhu_usdk/api/post.py
yunhu_usdk/api/send.py
yunhu_usdk/api/upload.py
yunhu_usdk/api/usdk_token.py
yunhu_usdk/api/pb2/__init__.py
yunhu_usdk/api/pb2/edit_message_pb2.py
yunhu_usdk/api/pb2/get_self_info_pb2.py
yunhu_usdk/api/pb2/recall_message_pb2.py
yunhu_usdk/api/pb2/send_message_pb2.py
yunhu_usdk/api.egg-info/PKG-INFO
yunhu_usdk/build/lib/api/__init__.py
yunhu_usdk/build/lib/api/edit.py
yunhu_usdk/build/lib/api/post.py
yunhu_usdk/build/lib/api/recall.py
yunhu_usdk/build/lib/api/send.py
yunhu_usdk/build/lib/api/upload.py
yunhu_usdk/build/lib/api/usdk_token.py
yunhu_usdk/build/lib/api/pb2/__init__.py
yunhu_usdk/build/lib/api/pb2/edit_message_pb2.py
yunhu_usdk/build/lib/api/pb2/send_message_pb2.py
yunhu_usdk-0.2.0.1.dist-info/licenses/LICENSE
yunhu_usdk-0.2.0.1.dist-info/WHEEL
yunhu_usdk-0.2.0.1.dist-info/METADATA
yunhu_usdk-0.2.0.1.dist-info/RECORD
