Metadata-Version: 2.4
Name: yunhu_usdk
Version: 0.2.0.1
Summary: 云湖SDK - 用于与云湖平台进行交互的Python SDK
Author-email: ShanFish <shanfishapp@qq.com>
License-Expression: MIT
License-File: LICENSE
Requires-Dist: aiohttp>=3.12.15
Requires-Dist: pillow>=11.3.0
Requires-Dist: asyncclick>=8.1.8.0
Requires-Dist: tinytag>=2.1.1
Requires-Dist: protobuf>=6.31.1
Project-URL: Home, https://github.com/shanfishapp/yunhu_usdk
